{
  "id": "english-jobs-germany",
  "englishOnly": true,
  "allowGenderMarker": true,
  "title": "English-Speaking Jobs in Germany & DACH",
  "tagline_de": "Englischsprachige Jobs bei Unternehmen in Deutschland, Österreich und der Schweiz — kein Deutsch erforderlich. **Täglich automatisch aktualisiert.**",
  "tagline_en": "A daily-updated list of English-language jobs at companies across Germany, Austria and Switzerland — no German required. Built for internationals and expats moving to the DACH region.",
  "count_label_de": "open English-speaking roles",
  "employer_label_de": "companies",
  "updated_label_de": "updated",
  "cta_heading": "Apply in 10 seconds",
  "cta_body": "Autofill any application and generate a matching, ATS-ready résumé with the",
  "cta_link_text": "Careerkit extension",
  "cta_url": "https://careerkit.me/en?utm_source=github&utm_campaign=english-jobs-germany",
  "star_line": "Useful? Star the repo so other internationals moving to Germany can find it.",
  "types_line": "Roles: **Working Student** · **Internship** · **Graduate** · **Junior** — all English-language.",
  "col_role": "Role",
  "col_company": "Company",
  "col_type": "Type",
  "col_posted": "Posted",
  "today_label": "today",
  "ago_prefix": "",
  "ago_suffix": "d ago",
  "apply_label": "Apply",
  "footer": "Auto-generated for internationals & expats job-hunting in the DACH region."
}
